gpjax/__init__.py
gpjax/_version.py
gpjax/abstractions.py
gpjax/config.py
gpjax/gaussian_distribution.py
gpjax/gps.py
gpjax/kernels.py
gpjax/likelihoods.py
gpjax/mean_functions.py
gpjax/natural_gradients.py
gpjax/parameters.py
gpjax/quadrature.py
gpjax/types.py
gpjax/utils.py
gpjax/variational_families.py
gpjax/variational_inference.py
gpjax_nightly-0.5.8.dist-info/METADATA
gpjax_nightly-0.5.8.dist-info/WHEEL
gpjax_nightly-0.5.8.dist-info/top_level.txt
gpjax_nightly-0.5.8.dist-info/RECORD
