Metadata-Version: 2.1
Name: gpjax-nightly
Version: 0.5.8
Summary: Didactic Gaussian processes in Jax.
Home-page: UNKNOWN
Author: Thomas Pinder
Author-email: t.pinder2@lancaster.ac.uk
License: LICENSE
Project-URL: Documentation, https://gpjax.readthedocs.io/en/latest/
Project-URL: Source, https://github.com/thomaspinder/GPJax
Keywords: gaussian-processes jax machine-learning bayesian
Platform: UNKNOWN
Requires-Python: >=3.7
Requires-Dist: jax (>=0.4.1)
Requires-Dist: jaxlib (>=0.4.1)
Requires-Dist: optax
Requires-Dist: jaxutils (>=0.0.6)
Requires-Dist: jaxkern (>=0.0.4)
Requires-Dist: distrax (>=0.1.2)
Requires-Dist: tqdm (>=4.0.0)
Requires-Dist: ml-collections (==0.1.0)
Requires-Dist: jaxtyping (>=0.0.2)
Requires-Dist: jaxlinop (>=0.0.3)
Requires-Dist: deprecation
Provides-Extra: cuda
Requires-Dist: jax[cuda] ; extra == 'cuda'
Provides-Extra: dev
Requires-Dist: black ; extra == 'dev'
Requires-Dist: isort ; extra == 'dev'
Requires-Dist: pylint ; extra == 'dev'
Requires-Dist: flake8 ; extra == 'dev'
Requires-Dist: pytest ; extra == 'dev'
Requires-Dist: networkx ; extra == 'dev'
Requires-Dist: pytest-cov ; extra == 'dev'
